MANIFEST.in
README
setup.py
django_rms.egg-info/PKG-INFO
django_rms.egg-info/SOURCES.txt
django_rms.egg-info/dependency_links.txt
django_rms.egg-info/not-zip-safe
django_rms.egg-info/requires.txt
django_rms.egg-info/top_level.txt
rms/__init__.py
rms/admin.py
rms/models.py
rms/urls.py
rms/views.py
rms/static/rms/css/style.css
rms/static/rms/img/arrow.png
rms/static/rms/js/jquery-1.6.1.min.js
rms/static/rms/js/jquery-1.7.1.min.js
rms/static/rms/js/rms.js
rms/templates/admin/rms/application/change_form.html
rms/templates/admin/rms/application/change_list.html
rms/templates/admin/rms/application/change_list_results.html
rms/templates/admin/rms/application/fieldset.html
rms/templatetags/__init__.py
rms/templatetags/applications_extra.py