Metadata-Version: 1.0
Name: django-rms
Version: 0.0.0
Summary: Django Rule Management System app
Home-page: http://github.com/psaavedra/django-rms
Author: Pablo Saavedra
Author-email: pablo.saavedra@treitos.com
License: UNKNOWN
Download-URL: https://github.com/psaavedra/django-rms/zipball/master
Keywords: rule manager django rms
Platform: UNKNOWN
Classifier: Development Status :: 2 - Pre-Alpha
Classifier: Framework :: Django
Classifier: License :: OSI Approved :: MIT License
Classifier: Operating System :: OS Independent
Classifier: Programming Language :: Python
Classifier: Topic :: Internet :: WWW/HTTP :: Dynamic Content
Classifier: Topic :: Software Development :: Libraries :: Python Modules
